TPL_Accounting/__init__.py
TPL_Accounting/settings.py
TPL_Accounting/urls.py
TPL_Accounting/wsgi.py
accounting/__init__.py
accounting/apps/__init__.py
accounting/apps/context_processors.py
accounting/apps/books/__init__.py
accounting/apps/books/admin.py
accounting/apps/books/apps.py
accounting/apps/books/calculators.py
accounting/apps/books/context_processors.py
accounting/apps/books/forms.py
accounting/apps/books/managers.py
accounting/apps/books/middlewares.py
accounting/apps/books/mixins.py
accounting/apps/books/models.py
accounting/apps/books/urls.py
accounting/apps/books/utils.py
accounting/apps/books/views.py
accounting/apps/books/migrations/0001_initial.py
accounting/apps/books/migrations/0002_auto_20210331_1839.py
accounting/apps/books/migrations/0003_auto_20210401_1004.py
accounting/apps/books/migrations/0004_auto_20210403_1928.py
accounting/apps/books/migrations/0005_auto_20210429_1206.py
accounting/apps/books/migrations/__init__.py
accounting/apps/books/templatetags/__init__.py
accounting/apps/books/templatetags/status_filters.py
accounting/apps/connect/__init__.py
accounting/apps/connect/login.py
accounting/apps/connect/middlewares.py
accounting/apps/connect/models.py
accounting/apps/connect/steps.py
accounting/apps/connect/urls.py
accounting/apps/connect/views.py
accounting/apps/people/__init__.py
accounting/apps/people/admin.py
accounting/apps/people/forms.py
accounting/apps/people/models.py
accounting/apps/people/urls.py
accounting/apps/people/views.py
accounting/apps/people/migrations/0001_initial.py
accounting/apps/people/migrations/0002_auto_20210403_1928.py
accounting/apps/people/migrations/__init__.py
accounting/apps/reports/__init__.py
accounting/apps/reports/admin.py
accounting/apps/reports/forms.py
accounting/apps/reports/models.py
accounting/apps/reports/urls.py
accounting/apps/reports/views.py
accounting/apps/reports/wrappers.py
accounting/apps/reports/migrations/0001_initial.py
accounting/apps/reports/migrations/0002_auto_20210403_1928.py
TPL_Accounting-1.3.dist-info/LICENSE
TPL_Accounting-1.3.dist-info/METADATA
TPL_Accounting-1.3.dist-info/WHEEL
TPL_Accounting-1.3.dist-info/top_level.txt
TPL_Accounting-1.3.dist-info/RECORD
